Metadata-Version: 2.4
Name: mseep-superset-mcp
Version: 0.1.4
Summary: Model Control Protocol (MCP) server for Apache Superset integration with AI assistants
Author-email: mseep <support@skydeck.ai>
License: MIT
Project-URL: Homepage, https://github.com/yourusername/superset-mcp
Project-URL: Issues, https://github.com/yourusername/superset-mcp/issues
Classifier: Development Status :: 4 - Beta
Classifier: Intended Audience :: Developers
Classifier: Programming Language :: Python :: 3
Classifier: License :: OSI Approved :: MIT License
Requires-Python: >=3.10
License-File: LICENSE
Requires-Dist: fastapi>=0.115.0
Requires-Dist: httpx>=0.28.0
Requires-Dist: mcp[cli]>=1.4.0
Requires-Dist: uvicorn>=0.34.0
Requires-Dist: python-dotenv>=1.0.0
Dynamic: license-file
